monnomdeprojet/__init__.py
monnomdeprojet/utils.py
mon_nom_de_projet-0.1.0.dist-info/METADATA
mon_nom_de_projet-0.1.0.dist-info/WHEEL
mon_nom_de_projet-0.1.0.dist-info/RECORD
